distribute_setup.py
setup.py
htpc_launcher.egg-info/PKG-INFO
htpc_launcher.egg-info/SOURCES.txt
htpc_launcher.egg-info/dependency_links.txt
htpc_launcher.egg-info/entry_points.txt
htpc_launcher.egg-info/top_level.txt
htpclauncher/__init__.py
htpclauncher/app.py
htpclauncher/command.py
htpclauncher/config.py
htpclauncher/irreader.py
htpclauncher/ostools.py
htpclauncher/processManager.py
htpclauncher/socketreader.py
test/test_app.py
test/test_command.py
test/test_irreader.py
test/test_processManager.py