Metadata-Version: 1.1
Name: htpc-launcher
Version: 1.1.0
Summary: Launch, and switch between, full-screen applications
Home-page: https://github.com/tctimmeh/htpc-launcher
Author: Tim Court
Author-email: tctimmeh@gmail.com
License: UNKNOWN
Platform: UNKNOWN
Classifier: Development Status :: 5 - Production/Stable
Classifier: Intended Audience :: End Users/Desktop
Classifier: Topic :: Multimedia
Classifier: License :: Public Domain
Classifier: Operating System :: POSIX :: Linux
